alpaca/__init__.py
alpaca/camera.py
alpaca/covercalibrator.py
alpaca/device.py
alpaca/discovery.py
alpaca/docenum.py
alpaca/dome.py
alpaca/exceptions.py
alpaca/filterwheel.py
alpaca/focuser.py
alpaca/management.py
alpaca/observingconditions.py
alpaca/rotator.py
alpaca/safetymonitor.py
alpaca/switch.py
alpaca/telescope.py
alpyca-3.1.1.dist-info/LICENSE.txt
alpyca-3.1.1.dist-info/METADATA
alpyca-3.1.1.dist-info/WHEEL
alpyca-3.1.1.dist-info/RECORD
