Metadata-Version: 2.1
Name: alpyca
Version: 3.1.1
Summary: API library for all ASCOM Alpaca devices, management, and discovery
Home-page: https://github.com/BobDenny/alpyca
License: LICENSE
Author: Robert B. Denny
Author-email: rdenny@dc3.com
Requires-Python: >=3.9,<4.0
Classifier: Intended Audience :: Developers
Classifier: License :: OSI Approved :: MIT License
Classifier: License :: Other/Proprietary License
Classifier: Operating System :: OS Independent
Classifier: Programming Language :: Python :: 3
Classifier: Programming Language :: Python :: 3.9
Classifier: Programming Language :: Python :: 3.10
Classifier: Programming Language :: Python :: 3.11
Classifier: Programming Language :: Python :: 3.12
Classifier: Topic :: Scientific/Engineering :: Astronomy
Requires-Dist: enum-tools (>=0.12.0,<0.13.0)
Requires-Dist: ifaddr (>=0.2.0,<0.3.0)
Requires-Dist: python-dateutil (>=2.8.2,<3.0.0)
Requires-Dist: requests (>=2.32.1,<3.0.0)
Requires-Dist: typing-extensions (>=4.12.0,<5.0.0)
Project-URL: ASCOM Initiative, https://ascom-standards.org/
Project-URL: ASCOM Developer Forum, https://ascomtalk.groups.io/g/Developer/
Project-URL: Bug Tracker, https://github.com/BobDenny/alpyca/issues
Project-URL: Documentation, https://ascom-standards.org/alpyca/index.html
Project-URL: Repository, https://github.com/BobDenny/alpyca
